mwklient/__init__.py
mwklient/client.py
mwklient/errors.py
mwklient/ex.py
mwklient/image.py
mwklient/listing.py
mwklient/page.py
mwklient/sleep.py
mwklient/util.py
mwklient/pages/__init__.py
mwklient/pages/edit.py
mwklient/pages/hazard.py
mwklient/pages/link.py
mwklient/pages/read.py
mwklient-0.1.0.dist-info/LICENSE.md
mwklient-0.1.0.dist-info/METADATA
mwklient-0.1.0.dist-info/WHEEL
mwklient-0.1.0.dist-info/top_level.txt
mwklient-0.1.0.dist-info/zip-safe
mwklient-0.1.0.dist-info/RECORD
