Metadata-Version: 2.1
Name: mwklient
Version: 0.1.0
Summary: MediaWiki API client
Home-page: https://github.com/lrusso96/mwklient
Author: Luigi Russo
Author-email: russo.1699981@studenti.unroma1.it
License: MIT
Keywords: mediawiki wikipedia
Platform: UNKNOWN
Classifier: Programming Language :: Python :: 3.5
Classifier: Programming Language :: Python :: 3.6
Classifier: Programming Language :: Python :: 3.7
Classifier: License :: OSI Approved :: MIT License
Requires-Dist: requests-oauthlib
Requires-Dist: six
